joshpdf/__init__.py
joshpdf/pdf2image.py
joshpdf/pdf2text.py
joshpdf-0.0.1.dist-info/METADATA
joshpdf-0.0.1.dist-info/WHEEL
joshpdf-0.0.1.dist-info/top_level.txt
joshpdf-0.0.1.dist-info/RECORD
