Metadata-Version: 2.4
Name: joshpdf
Version: 0.0.1
Summary: This is the homepage of our project
Author: Josh
Dynamic: author
Dynamic: summary
